LaravelYuanmaJiexi/README.md
LaravelYuanmaJiexi/__init__.py
LaravelYuanmaJiexi/__main__.py
LaravelYuanmaJiexi/file.epub
LaravelYuanmaJiexi/index.html
LaravelYuanmaJiexi/css/__init__.py
LaravelYuanmaJiexi/css/annotations.css
LaravelYuanmaJiexi/css/main.css
LaravelYuanmaJiexi/css/normalize.css
LaravelYuanmaJiexi/css/popup.css
LaravelYuanmaJiexi/font/__init__.py
LaravelYuanmaJiexi/font/fontello.eot
LaravelYuanmaJiexi/font/fontello.svg
LaravelYuanmaJiexi/font/fontello.ttf
LaravelYuanmaJiexi/font/fontello.woff
LaravelYuanmaJiexi/img/__init__.py
LaravelYuanmaJiexi/img/annotator-glyph-sprite.png
LaravelYuanmaJiexi/img/annotator-icon-sprite.png
LaravelYuanmaJiexi/img/apple-touch-icon.png
LaravelYuanmaJiexi/img/cancelfullscreen.png
LaravelYuanmaJiexi/img/close.png
LaravelYuanmaJiexi/img/fullscreen.png
LaravelYuanmaJiexi/img/loader.gif
LaravelYuanmaJiexi/img/menu-icon.png
LaravelYuanmaJiexi/img/save.png
LaravelYuanmaJiexi/img/saved.png
LaravelYuanmaJiexi/img/settings-s.png
LaravelYuanmaJiexi/img/settings.png
LaravelYuanmaJiexi/img/star.png
LaravelYuanmaJiexi/js/__init__.py
LaravelYuanmaJiexi/js/epub.js
LaravelYuanmaJiexi/js/epub.min.js
LaravelYuanmaJiexi/js/epub.min.map
LaravelYuanmaJiexi/js/hooks.min.js
LaravelYuanmaJiexi/js/hooks.min.map
LaravelYuanmaJiexi/js/reader.js
LaravelYuanmaJiexi/js/reader.js.map
LaravelYuanmaJiexi/js/reader.min.js
LaravelYuanmaJiexi/js/reader.min.map
LaravelYuanmaJiexi/js/hooks/__init__.py
LaravelYuanmaJiexi/js/hooks/extensions/__init__.py
LaravelYuanmaJiexi/js/hooks/extensions/highlight.js
LaravelYuanmaJiexi/js/libs/__init__.py
LaravelYuanmaJiexi/js/libs/jquery.min.js
LaravelYuanmaJiexi/js/libs/localforage.min.js
LaravelYuanmaJiexi/js/libs/screenfull.js
LaravelYuanmaJiexi/js/libs/screenfull.min.js
LaravelYuanmaJiexi/js/libs/zip.min.js
LaravelYuanmaJiexi/js/plugins/__init__.py
LaravelYuanmaJiexi/js/plugins/hypothesis.js
LaravelYuanmaJiexi/js/plugins/search.js
laravel_yuanma_jiexi-2024.3.3.0.dist-info/METADATA
laravel_yuanma_jiexi-2024.3.3.0.dist-info/WHEEL
laravel_yuanma_jiexi-2024.3.3.0.dist-info/entry_points.txt
laravel_yuanma_jiexi-2024.3.3.0.dist-info/top_level.txt
laravel_yuanma_jiexi-2024.3.3.0.dist-info/RECORD
